{
"meta":{"test_sets":[],"test_metrics":[],"learn_metrics":[{"best_value":"Min","name":"RMSE"}],"launch_mode":"Train","parameters":"","iteration_count":100,"learn_sets":["learn"],"name":"experiment"},
"iterations":[
{"learn":[14.005006],"iteration":0,"passed_time":0.002297598854,"remaining_time":0.2274622865},
{"learn":[13.14441192],"iteration":1,"passed_time":0.004058551707,"remaining_time":0.1988690336},
{"learn":[12.34258257],"iteration":2,"passed_time":0.005786549494,"remaining_time":0.1870984336},
{"learn":[11.64527793],"iteration":3,"passed_time":0.00722090949,"remaining_time":0.1733018278},
{"learn":[11.02766183],"iteration":4,"passed_time":0.009201009032,"remaining_time":0.1748191716},
{"learn":[10.43485794],"iteration":5,"passed_time":0.010772978,"remaining_time":0.1687766553},
{"learn":[9.890641275],"iteration":6,"passed_time":0.01224478942,"remaining_time":0.1626807737},
{"learn":[9.492161212],"iteration":7,"passed_time":0.01387667562,"remaining_time":0.1595817696},
{"learn":[9.105082953],"iteration":8,"passed_time":0.01544692368,"remaining_time":0.1561855617},
{"learn":[8.674157135],"iteration":9,"passed_time":0.01700674888,"remaining_time":0.1530607399},
{"learn":[8.341743544],"iteration":10,"passed_time":0.0186198892,"remaining_time":0.1506518308},
{"learn":[8.049372916],"iteration":11,"passed_time":0.02018417882,"remaining_time":0.1480173114},
{"learn":[7.757318612],"iteration":12,"passed_time":0.02171519575,"remaining_time":0.1453247716},
{"learn":[7.522206899],"iteration":13,"passed_time":0.0236010735,"remaining_time":0.1449780229},
{"learn":[7.297756655],"iteration":14,"passed_time":0.025227313,"remaining_time":0.1429547737},
{"learn":[7.088359431],"iteration":15,"passed_time":0.02675108164,"remaining_time":0.1404431786},
{"learn":[6.882113791],"iteration":16,"passed_time":0.02851284537,"remaining_time":0.1392097745},
{"learn":[6.704728832],"iteration":17,"passed_time":0.03030618021,"remaining_time":0.1380614876},
{"learn":[6.563881962],"iteration":18,"passed_time":0.03211148909,"remaining_time":0.1368963482},
{"learn":[6.418790279],"iteration":19,"passed_time":0.03386532223,"remaining_time":0.1354612889},
{"learn":[6.315756953],"iteration":20,"passed_time":0.0357655058,"remaining_time":0.1345464266},
{"learn":[6.210157751],"iteration":21,"passed_time":0.03737426152,"remaining_time":0.1325087454},
{"learn":[6.115058449],"iteration":22,"passed_time":0.03936020944,"remaining_time":0.1317711359},
{"learn":[6.014819884],"iteration":23,"passed_time":0.04110076946,"remaining_time":0.1301524366},
{"learn":[5.93117229],"iteration":24,"passed_time":0.04307987074,"remaining_time":0.1292396122},
{"learn":[5.844857622],"iteration":25,"passed_time":0.04577667048,"remaining_time":0.1302874468},
{"learn":[5.771145213],"iteration":26,"passed_time":0.04739705909,"remaining_time":0.1281476042},
{"learn":[5.704018229],"iteration":27,"passed_time":0.04883489953,"remaining_time":0.1255754559},
{"learn":[5.665806474],"iteration":28,"passed_time":0.05024208393,"remaining_time":0.1230064814},
{"learn":[5.616500369],"iteration":29,"passed_time":0.05164702309,"remaining_time":0.1205097206},
{"learn":[5.558023666],"iteration":30,"passed_time":0.05324074951,"remaining_time":0.1185036038},
{"learn":[5.510080976],"iteration":31,"passed_time":0.05449973737,"remaining_time":0.1158119419},
{"learn":[5.468747792],"iteration":32,"passed_time":0.05586327578,"remaining_time":0.1134193781},
{"learn":[5.429275534],"iteration":33,"passed_time":0.05707925375,"remaining_time":0.1108009043},
{"learn":[5.402117324],"iteration":34,"passed_time":0.05830451348,"remaining_time":0.1082798108},
{"learn":[5.367635151],"iteration":35,"passed_time":0.0594459911,"remaining_time":0.105681762},
{"learn":[5.345181232],"iteration":36,"passed_time":0.06051105925,"remaining_time":0.1030323441},
{"learn":[5.319151269],"iteration":37,"passed_time":0.06156737921,"remaining_time":0.1004520398},
{"learn":[5.296134146],"iteration":38,"passed_time":0.06261069496,"remaining_time":0.09792954852},
{"learn":[5.269629003],"iteration":39,"passed_time":0.06368090228,"remaining_time":0.09552135342},
{"learn":[5.251147059],"iteration":40,"passed_time":0.06475470769,"remaining_time":0.09318360375},
{"learn":[5.248003302],"iteration":41,"passed_time":0.06521762389,"remaining_time":0.09006243299},
{"learn":[5.232376509],"iteration":42,"passed_time":0.06622168664,"remaining_time":0.08778223578},
{"learn":[5.213524255],"iteration":43,"passed_time":0.06727388165,"remaining_time":0.08562130392},
{"learn":[5.189691584],"iteration":44,"passed_time":0.068425099,"remaining_time":0.08363067655},
{"learn":[5.166052198],"iteration":45,"passed_time":0.06950726607,"remaining_time":0.08159548625},
{"learn":[5.140406659],"iteration":46,"passed_time":0.07062891301,"remaining_time":0.07964536998},
{"learn":[5.118929684],"iteration":47,"passed_time":0.07157557097,"remaining_time":0.07754020189},
{"learn":[5.108792602],"iteration":48,"passed_time":0.07249345176,"remaining_time":0.07545236816},
{"learn":[5.098141225],"iteration":49,"passed_time":0.07344363808,"remaining_time":0.07344363808},
{"learn":[5.085926393],"iteration":50,"passed_time":0.07421508441,"remaining_time":0.07130468894},
{"learn":[5.067816804],"iteration":51,"passed_time":0.07498952634,"remaining_time":0.06922110124},
{"learn":[5.049834901],"iteration":52,"passed_time":0.07581822956,"remaining_time":0.06723503376},
{"learn":[5.03838627],"iteration":53,"passed_time":0.07657413905,"remaining_time":0.06522982215},
{"learn":[5.033534248],"iteration":54,"passed_time":0.07708139027,"remaining_time":0.06306659204},
{"learn":[5.023726885],"iteration":55,"passed_time":0.07788092306,"remaining_time":0.06119215383},
{"learn":[5.01290392],"iteration":56,"passed_time":0.07867042118,"remaining_time":0.05934786159},
{"learn":[5.005569127],"iteration":57,"passed_time":0.07942381571,"remaining_time":0.05751379758},
{"learn":[4.989969032],"iteration":58,"passed_time":0.08014811374,"remaining_time":0.05569614684},
{"learn":[4.976762446],"iteration":59,"passed_time":0.08079561494,"remaining_time":0.05386374329},
{"learn":[4.967222715],"iteration":60,"passed_time":0.08141229203,"remaining_time":0.05205048179},
{"learn":[4.954407599],"iteration":61,"passed_time":0.08206271321,"remaining_time":0.05029650165},
{"learn":[4.942125056],"iteration":62,"passed_time":0.08270391397,"remaining_time":0.04857213995},
{"learn":[4.930230716],"iteration":63,"passed_time":0.08344886196,"remaining_time":0.04693998485},
{"learn":[4.921695642],"iteration":64,"passed_time":0.0842261659,"remaining_time":0.04535255087},
{"learn":[4.906405625],"iteration":65,"passed_time":0.08483384272,"remaining_time":0.04370228261},
{"learn":[4.894330248],"iteration":66,"passed_time":0.0854339301,"remaining_time":0.04207939841},
{"learn":[4.88211557],"iteration":67,"passed_time":0.08602773804,"remaining_time":0.04048364143},
{"learn":[4.877946398],"iteration":68,"passed_time":0.08663954065,"remaining_time":0.03892501102},
{"learn":[4.863182126],"iteration":69,"passed_time":0.08724247155,"remaining_time":0.03738963066},
{"learn":[4.84646533],"iteration":70,"passed_time":0.08781943938,"remaining_time":0.03586991186},
{"learn":[4.838014752],"iteration":71,"passed_time":0.08844832074,"remaining_time":0.03439656918},
{"learn":[4.82981137],"iteration":72,"passed_time":0.08903824237,"remaining_time":0.03293195266},
{"learn":[4.817094767],"iteration":73,"passed_time":0.0896475006,"remaining_time":0.03149777048},
{"learn":[4.808314151],"iteration":74,"passed_time":0.09022533728,"remaining_time":0.03007511243},
{"learn":[4.796235023],"iteration":75,"passed_time":0.09082336849,"remaining_time":0.02868106373},
{"learn":[4.784434534],"iteration":76,"passed_time":0.09141299519,"remaining_time":0.02730518038},
{"learn":[4.774402487],"iteration":77,"passed_time":0.09205728734,"remaining_time":0.02596487592},
{"learn":[4.76731896],"iteration":78,"passed_time":0.09266558177,"remaining_time":0.024632623},
{"learn":[4.75934113],"iteration":79,"passed_time":0.09327381569,"remaining_time":0.02331845392},
{"learn":[4.754106378],"iteration":80,"passed_time":0.09388990038,"remaining_time":0.02202355688},
{"learn":[4.744002932],"iteration":81,"passed_time":0.0944837537,"remaining_time":0.02074033618},
{"learn":[4.731700554],"iteration":82,"passed_time":0.09507062427,"remaining_time":0.01947229654},
{"learn":[4.723284153],"iteration":83,"passed_time":0.09564768453,"remaining_time":0.01821860658},
{"learn":[4.712232782],"iteration":84,"passed_time":0.0962471022,"remaining_time":0.01698478274},
{"learn":[4.703046867],"iteration":85,"passed_time":0.09681903085,"remaining_time":0.01576123758},
{"learn":[4.698601855],"iteration":86,"passed_time":0.09741115067,"remaining_time":0.01455568918},
{"learn":[4.692429407],"iteration":87,"passed_time":0.09801977701,"remaining_time":0.01336633323},
{"learn":[4.675027364],"iteration":88,"passed_time":0.09879985472,"remaining_time":0.012211218},
{"learn":[4.662368584],"iteration":89,"passed_time":0.09938632195,"remaining_time":0.01104292466},
{"learn":[4.646206172],"iteration":90,"passed_time":0.09997000196,"remaining_time":0.009887143051},
{"learn":[4.641245848],"iteration":91,"passed_time":0.1005509477,"remaining_time":0.008743560669},
{"learn":[4.633900435],"iteration":92,"passed_time":0.1011520686,"remaining_time":0.007613596563},
{"learn":[4.624738236],"iteration":93,"passed_time":0.1017635931,"remaining_time":0.006495548495},
{"learn":[4.612798287],"iteration":94,"passed_time":0.1023483638,"remaining_time":0.005386755989},
{"learn":[4.605222001],"iteration":95,"passed_time":0.1029453816,"remaining_time":0.004289390901},
{"learn":[4.601725912],"iteration":96,"passed_time":0.1035091066,"remaining_time":0.003201312575},
{"learn":[4.59722371],"iteration":97,"passed_time":0.1040565099,"remaining_time":0.002123602243},
{"learn":[4.580235665],"iteration":98,"passed_time":0.1046334676,"remaining_time":0.001056903713},
{"learn":[4.57591791],"iteration":99,"passed_time":0.1051955793,"remaining_time":0}
]}